<escenarioSimulacion>
   <identEscenario>modeloOrg_JerarquicoNumRobts_4NumVicts_9</identEscenario>
   <modeloOrganizativo>Jerarquico</modeloOrganizativo>
   <numRobots>4</numRobots>
   <numVictimas>9</numVictimas>
   <robots key="JerarquicorobotSubordinado4">
      <robotStatus>
         <idRobot>JerarquicorobotSubordinado4</idRobot>
         <idRobotRol>indefinido</idRobotRol>
         <availableEnergy>0</availableEnergy>
         <robotCoordinateActual>
            <x>53.0</x>
            <y>146.0</y>
            <z>0.5</z>
         </robotCoordinateActual>
         <robotCapabilities class="java.util.ArrayList">
            <robotCapability nombre="radar">
               <descripcion>radar del robot</descripcion>
            </robotCapability>
         </robotCapabilities>
      </robotStatus>
   </robots>
   <robots key="JerarquicorobotSubordinado3">
      <robotStatus>
         <idRobot>JerarquicorobotSubordinado3</idRobot>
         <idRobotRol>indefinido</idRobotRol>
         <availableEnergy>0</availableEnergy>
         <robotCoordinateActual>
            <x>129.0</x>
            <y>480.0</y>
            <z>0.5</z>
         </robotCoordinateActual>
         <robotCapabilities class="java.util.ArrayList">
            <robotCapability nombre="radar">
               <descripcion>radar del robot</descripcion>
            </robotCapability>
         </robotCapabilities>
      </robotStatus>
   </robots>
   <robots key="JerarquicorobotSubordinado2">
      <robotStatus>
         <idRobot>JerarquicorobotSubordinado2</idRobot>
         <idRobotRol>indefinido</idRobotRol>
         <availableEnergy>0</availableEnergy>
         <robotCoordinateActual>
            <x>138.0</x>
            <y>289.0</y>
            <z>0.5</z>
         </robotCoordinateActual>
         <robotCapabilities class="java.util.ArrayList">
            <robotCapability nombre="radar">
               <descripcion>radar del robot</descripcion>
            </robotCapability>
         </robotCapabilities>
      </robotStatus>
   </robots>
   <robots key="JerarquicorobotSubordinado1">
      <robotStatus>
         <idRobot>JerarquicorobotSubordinado1</idRobot>
         <idRobotRol>indefinido</idRobotRol>
         <availableEnergy>0</availableEnergy>
         <robotCoordinateActual>
            <x>187.0</x>
            <y>137.0</y>
            <z>0.5</z>
         </robotCoordinateActual>
         <robotCapabilities class="java.util.ArrayList">
            <robotCapability nombre="radar">
               <descripcion>radar del robot</descripcion>
            </robotCapability>
         </robotCapabilities>
      </robotStatus>
   </robots>
   <victimas key="Victima9">
      <victim>
         <name>Victima9</name>
         <coordinateVictim>
            <x>833.0</x>
            <y>396.0</y>
            <z>0.5</z>
         </coordinateVictim>
         <RequiredCompetencies class="java.util.ArrayList"/>
         <priority>0</priority>
         <tiempoDeVida>6000</tiempoDeVida>
      </victim>
   </victimas>
   <victimas key="Victima8">
      <victim>
         <name>Victima8</name>
         <coordinateVictim>
            <x>642.0</x>
            <y>308.0</y>
            <z>0.5</z>
         </coordinateVictim>
         <RequiredCompetencies class="java.util.ArrayList"/>
         <priority>0</priority>
         <tiempoDeVida>6000</tiempoDeVida>
      </victim>
   </victimas>
   <victimas key="Victima7">
      <victim>
         <name>Victima7</name>
         <coordinateVictim>
            <x>734.0</x>
            <y>191.0</y>
            <z>0.5</z>
         </coordinateVictim>
         <RequiredCompetencies class="java.util.ArrayList"/>
         <priority>0</priority>
         <tiempoDeVida>6000</tiempoDeVida>
      </victim>
   </victimas>
   <victimas key="Victima6">
      <victim>
         <name>Victima6</name>
         <coordinateVictim>
            <x>772.0</x>
            <y>191.0</y>
            <z>0.5</z>
         </coordinateVictim>
         <RequiredCompetencies class="java.util.ArrayList"/>
         <priority>0</priority>
         <tiempoDeVida>6000</tiempoDeVida>
      </victim>
   </victimas>
   <victimas key="Victima5">
      <victim>
         <name>Victima5</name>
         <coordinateVictim>
            <x>692.0</x>
            <y>339.0</y>
            <z>0.5</z>
         </coordinateVictim>
         <RequiredCompetencies class="java.util.ArrayList"/>
         <priority>0</priority>
         <tiempoDeVida>6000</tiempoDeVida>
      </victim>
   </victimas>
   <victimas key="Victima4">
      <victim>
         <name>Victima4</name>
         <coordinateVictim>
            <x>795.0</x>
            <y>177.0</y>
            <z>0.5</z>
         </coordinateVictim>
         <RequiredCompetencies class="java.util.ArrayList"/>
         <priority>0</priority>
         <tiempoDeVida>6000</tiempoDeVida>
      </victim>
   </victimas>
   <victimas key="Victima3">
      <victim>
         <name>Victima3</name>
         <coordinateVictim>
            <x>887.0</x>
            <y>281.0</y>
            <z>0.5</z>
         </coordinateVictim>
         <RequiredCompetencies class="java.util.ArrayList"/>
         <priority>0</priority>
         <tiempoDeVida>6000</tiempoDeVida>
      </victim>
   </victimas>
   <victimas key="Victima2">
      <victim>
         <name>Victima2</name>
         <coordinateVictim>
            <x>722.0</x>
            <y>405.0</y>
            <z>0.5</z>
         </coordinateVictim>
         <RequiredCompetencies class="java.util.ArrayList"/>
         <priority>0</priority>
         <tiempoDeVida>6000</tiempoDeVida>
      </victim>
   </victimas>
   <victimas key="Victima1">
      <victim>
         <name>Victima1</name>
         <coordinateVictim>
            <x>678.0</x>
            <y>157.0</y>
            <z>0.5</z>
         </coordinateVictim>
         <RequiredCompetencies class="java.util.ArrayList"/>
         <priority>0</priority>
         <tiempoDeVida>6000</tiempoDeVida>
      </victim>
   </victimas>
   <obstaculos key="0">
      <lineaObstaculo>
         <ini>
            <x>446.0</x>
            <y>149.0</y>
            <z>0.5</z>
         </ini>
         <fin>
            <x>446.0</x>
            <y>553.0</y>
            <z>0.5</z>
         </fin>
         <valueid>0</valueid>
      </lineaObstaculo>
   </obstaculos>
   <obstaculos key="1">
      <lineaObstaculo>
         <ini>
            <x>519.0</x>
            <y>285.0</y>
            <z>0.5</z>
         </ini>
         <fin>
            <x>519.0</x>
            <y>623.0</y>
            <z>0.5</z>
         </fin>
         <valueid>1</valueid>
      </lineaObstaculo>
   </obstaculos>
   <obstaculos key="inicial">
      <lineaObstaculo>
         <ini>
            <x>0.0</x>
            <y>0.0</y>
            <z>0.5</z>
         </ini>
         <fin>
            <x>0.0</x>
            <y>0.0</y>
            <z>0.5</z>
         </fin>
         <valueid>inicial</valueid>
      </lineaObstaculo>
   </obstaculos>
</escenarioSimulacion>